[
  {
    "id": "The-Big-Step",
    "titulo": "DESCARGAR The Big Step [S2 - v0.3] PARA ANDROID Y PC EN ESPAÑOL",
    "version": "S2 - v0.3",
    "autor": "Partedes",
    "fecha": "2 jul 2026",
    "portada": "https://i.ibb.co/fVM8xY6y/o1.avif",
    "galeria": [
      "https://i.ibb.co/WvSHtSGY/b64.avif",
      "https://i.ibb.co/n86ycSJs/a276.avif",
      "https://i.ibb.co/zVvL9pmH/a140.avif"
    ],
    "descripcion": "Sigue las aventuras de Samantha en la universidad, en el trabajo y en casa...",
    "tags": ["3DCG", "Tetas Grandes", "Prota Femenina", "Corrupción", "Virgen", "Voyeurismo", "Incesto", "Milf"],
    "vistas": 0,
    "descargas": 0,
    "likes": 0,
    "dislikes": 0,
    "descarga_pc": "https://pixeldrain.com/u/KQyJbsW9",
    "descarga_apk": "https://pixeldrain.com/u/LAyhcwup"
  }
]
